{"resourceType":"ValueSet","expansion":{"identifier":"urn:uuid:95614361-3a4b-44c2-a109-00ca3c5dc6db","timestamp":"2016-09-01T07:03:59Z","parameter":[{"name":"version","valueUri":"http://snomed.info/sct?version=http://snomed.info/sct/32506021000036107/version/20160430"}],"contains":[{"system":"http://snomed.info/sct","code":"420387003","display":"Extraprostatic extension of tumor present, non-focal"},{"system":"http://snomed.info/sct","code":"420366008","display":"Extraprostatic extension of tumor present, focal"}]}}